NgrokLinkify/__init__.py
NgrokLinkify/__main__.py
NgrokLinkify/base.py
NgrokLinkify/linkify.py
NgrokLinkify-1.0.dist-info/LICENSE
NgrokLinkify-1.0.dist-info/METADATA
NgrokLinkify-1.0.dist-info/WHEEL
NgrokLinkify-1.0.dist-info/entry_points.txt
NgrokLinkify-1.0.dist-info/top_level.txt
NgrokLinkify-1.0.dist-info/RECORD
