Metadata-Version: 2.1
Name: NgrokLinkify
Version: 1.0
Summary: A package to expose your services to the internet using Ngrok
Home-page: https://github.com/bagdeabhishek/telegram_bot
Author: Abhishek Bagade
Author-email: bagdeabhishek@gmail.com
License: UNKNOWN
Project-URL: Blog, https://www.abagade.com/ngrok/
Project-URL: Github, https://github.com/bagdeabhishek/telegram_bot
Platform: UNKNOWN
Classifier: Programming Language :: Python :: 3
Classifier: License :: OSI Approved :: MIT License
Classifier: Operating System :: OS Independent
Requires-Python: >=3.7
License-File: LICENSE
